phylorank/__init__.py
phylorank/__main__.py
phylorank/bl_dist.py
phylorank/common.py
phylorank/decorate.py
phylorank/main.py
phylorank/mark_tree.py
phylorank/newick.py
phylorank/outliers.py
phylorank/rd_ranks.py
phylorank/rel_dist.py
phylorank/rogue_test.py
phylorank/viral_taxonomy.py
phylorank/plot/__init__.py
phylorank/plot/robustness_plot.py
phylorank-0.1.12.data/data/LICENSE
tests/__init__.py
tests/test___main__.py
phylorank-0.1.12.dist-info/LICENSE
phylorank-0.1.12.dist-info/METADATA
phylorank-0.1.12.dist-info/WHEEL
phylorank-0.1.12.dist-info/entry_points.txt
phylorank-0.1.12.dist-info/top_level.txt
phylorank-0.1.12.dist-info/RECORD
