Metadata-Version: 2.1
Name: phylorank
Version: 0.1.12
Summary: Assigns taxonomic ranks based on evolutionary divergence.
Home-page: https://github.com/dparks1134/PhyloRank
Author: Donovan Parks
Author-email: donovan.parks@gmail.com
License: GPL3
Project-URL: Bug Tracker, https://github.com/dparks1134/PhyloRank/issues
Project-URL: Documentation, https://github.com/dparks1134/PhyloRank
Project-URL: Source Code, https://github.com/dparks1134/PhyloRank
Keywords: phylogenetics taxonomy relative evolutionary divergence tree decorate decoration
Platform: UNKNOWN
Classifier: Development Status :: 4 - Beta
Classifier: Intended Audience :: Science/Research
Classifier: License :: OSI Approved :: GNU General Public License v3 (GPLv3)
Classifier: Natural Language :: English
Classifier: Operating System :: OS Independent
Classifier: Programming Language :: Python :: 3.6
Classifier: Programming Language :: Python :: 3.7
Classifier: Programming Language :: Python :: 3.8
Classifier: Programming Language :: Python :: 3.9
Classifier: Topic :: Scientific/Engineering :: Bio-Informatics
Requires-Python: >=3.6
Requires-Dist: biolib (>=0.1.0)
Requires-Dist: numpy
Requires-Dist: matplotlib (<3.5.0)
Requires-Dist: dendropy (>=4.1.0)
Requires-Dist: scipy
Requires-Dist: mpld3 (>=0.5.2)
